{
  "candidate_selection_authority_granted": false,
  "codeai_disposition": "intent_aligned_dataflow_context_pack_built",
  "completeness_claimed": false,
  "context_pack_digest": "9f8d9d91bd51ee67ef93ff5b45274cbc4b1e303073d60795381f7154f307966c",
  "correctness_claimed": false,
  "dataflow_edge_count": 26,
  "execution_authority_granted": false,
  "network_access_performed": false,
  "operating_mode": "context_only",
  "policy_digest": "5dd90fbad8b68857919c90819b9b1619d4647664be5bdefde3dd5f0f93384864",
  "profile_version": "CodeAI Intent-Aligned Dataflow Context Pack v0.2",
  "query_lineage_node_count": 6,
  "query_stages": [
    "intent",
    "hypothesis",
    "hypothesis",
    "symbol",
    "dependency",
    "dataflow"
  ],
  "receipt_digest": "096f8a00c3c92dc42d5a474eec1b032795b302d16d0bc5a9ea6a4f618ff89e23",
  "repository_full_name": "itakura-hidetoshi/KuuOS",
  "repository_mutation_performed": false,
  "repository_observation_read_only": true,
  "repository_snapshot_bytes": 1578,
  "representativeness_claimed": false,
  "request_digest": "d9ca0a54fa407b1a47665761214842319e84d52baa62210d8ecf786878a8ece7",
  "resolved_dependency_path_count": 7,
  "schema_version": "v0.2",
  "secret_material_read": false,
  "selected_file_count": 6,
  "selected_paths": [
    "docs/order_pipeline_dataflow.md",
    "runtime/order_pipeline.py",
    "formal/KUOS/CodeAI/OrderPipelineReferenceV0_2.lean",
    "runtime/pricing.py",
    "formal/KUOS/CodeAI/PricingReferenceV0_2.lean",
    "tests/test_order_pipeline.py"
  ],
  "source_commit_sha": "1d953b9d8383b5fc1ab42431c6fa9bec39a83b61",
  "symbol_digest_count": 6,
  "total_context_bytes": 1539
}
